{"nodes": [{"id": "globe_earth_icon", "label": "Globe Earth Icon", "file_type": "image", "source_file": "consentflow-frontend/public/globe.svg", "source_location": null, "source_url": null, "captured_at": null, "author": null, "contributor": null}, {"id": "globe_latitude_longitude_grid", "label": "Latitude and Longitude Grid", "file_type": "image", "source_file": "consentflow-frontend/public/globe.svg", "source_location": null, "source_url": null, "captured_at": null, "author": null, "contributor": null}, {"id": "globe_circular_world_boundary", "label": "Circular World Boundary", "file_type": "image", "source_file": "consentflow-frontend/public/globe.svg", "source_location": null, "source_url": null, "captured_at": null, "author": null, "contributor": null}], "edges": [{"source": "globe_earth_icon", "target": "globe_latitude_longitude_grid", "relation": "references", "confidence": "EXTRACTED", "confidence_score": 1.0, "source_file": "consentflow-frontend/public/globe.svg", "source_location": null, "weight": 1.0}, {"source": "globe_earth_icon", "target": "globe_circular_world_boundary", "relation": "references", "confidence": "EXTRACTED", "confidence_score": 1.0, "source_file": "consentflow-frontend/public/globe.svg", "source_location": null, "weight": 1.0}, {"source": "globe_latitude_longitude_grid", "target": "globe_circular_world_boundary", "relation": "conceptually_related_to", "confidence": "INFERRED", "confidence_score": 0.75, "source_file": "consentflow-frontend/public/globe.svg", "source_location": null, "weight": 1.0}], "hyperedges": []}